[
  {
    "title": "Original Score for 'Marked' (2021), MIDI Mockup",
    "description": "",
    "youtubeId": "s2zUfU0UJcs"
  },
  {
    "title": "Game Cue from \"Dante's Inferno\"",
    "description": "",
    "youtubeId": "jids_cSE05s"
  },
  {
    "title": "Ministry Battle Scene from \"Harry Potter\"",
    "description": "",
    "youtubeId": "_4HFZ_mE6_E"
  },
  {
    "title": "Ticket Scene from \"Polar Express\"",
    "description": "",
    "youtubeId": "jcZGtEFA6tY"
  },
  {
    "title": "Train Scene from \"LION\"",
    "description": "",
    "youtubeId": "vjTCGM3M0Ik"
  }
]
